table_reconstruction/__init__.py
table_reconstruction/__version__.py
table_reconstruction/line_segmentation/__init__.py
table_reconstruction/line_segmentation/line_segment.py
table_reconstruction/line_segmentation/utils.py
table_reconstruction/line_segmentation/unet/__init__.py
table_reconstruction/line_segmentation/unet/resunet.py
table_reconstruction/line_segmentation/unet/unet_parts.py
table_reconstruction/output/__init__.py
table_reconstruction/output/cell.py
table_reconstruction/output/element.py
table_reconstruction/output/table.py
table_reconstruction/table_detection/__init__.py
table_reconstruction/table_detection/detector.py
table_reconstruction/table_detection/preprocess.py
table_reconstruction/table_detection/utils.py
table_reconstruction/table_detection/yolov5/__init__.py
table_reconstruction/table_detection/yolov5/hubconf.py
table_reconstruction/table_detection/yolov5/models/__init__.py
table_reconstruction/table_detection/yolov5/models/common.py
table_reconstruction/table_detection/yolov5/models/experimental.py
table_reconstruction/table_detection/yolov5/models/utils.py
table_reconstruction/table_detection/yolov5/models/yolo.py
table_reconstruction/utils/__init__.py
table_reconstruction/utils/cell_utils.py
table_reconstruction/utils/lines_utils.py
table_reconstruction/utils/mask_utils.py
table_reconstruction/utils/table_utils.py
table_reconstruction-0.0.4.dist-info/LICENSE
table_reconstruction-0.0.4.dist-info/METADATA
table_reconstruction-0.0.4.dist-info/WHEEL
table_reconstruction-0.0.4.dist-info/top_level.txt
table_reconstruction-0.0.4.dist-info/RECORD
